asterisk_doorphone/__init__.py
asterisk_doorphone/assign_buttons.py
asterisk_doorphone/asterisk_ami.py
asterisk_doorphone/configure.py
asterisk_doorphone/usb_keyboard.py
asterisk_doorphone-0.1.5.dist-info/WHEEL
asterisk_doorphone-0.1.5.dist-info/METADATA
asterisk_doorphone-0.1.5.dist-info/RECORD
