Metadata-Version: 2.1
Name: asterisk_doorphone
Version: 0.1.5
Summary: asterisk-doorphone
Author-email: Jonatan Garbuyo <jonatangarbuyo@gmail.com>
Classifier: License :: OSI Approved :: MIT License
Requires-Dist: evdev==1.4.0
Requires-Dist: pick==1.0.0
